chaoslib/__init__.py
chaoslib/activity.py
chaoslib/caching.py
chaoslib/configuration.py
chaoslib/control/__init__.py
chaoslib/control/python.py
chaoslib/deprecation.py
chaoslib/discovery/__init__.py
chaoslib/discovery/discover.py
chaoslib/discovery/package.py
chaoslib/exceptions.py
chaoslib/exit.py
chaoslib/experiment.py
chaoslib/extension.py
chaoslib/hypothesis.py
chaoslib/info.py
chaoslib/loader.py
chaoslib/log.py
chaoslib/notification.py
chaoslib/provider/__init__.py
chaoslib/provider/http.py
chaoslib/provider/process.py
chaoslib/provider/python.py
chaoslib/rollback.py
chaoslib/run.py
chaoslib/secret.py
chaoslib/settings.py
chaoslib/types.py
chaostoolkit_lib-1.43.1.dist-info/METADATA
chaostoolkit_lib-1.43.1.dist-info/WHEEL
chaostoolkit_lib-1.43.1.dist-info/licenses/LICENSE
chaostoolkit_lib-1.43.1.dist-info/RECORD
