Metadata-Version: 2.1
Name: chaostoolkit-lib
Version: 1.43.1
Summary: Chaos Toolkit core library
Author-Email: Chaos Toolkit <contact@chaostoolkit.org>, Sylvain Hellegouarch <sh@defuze.org>
License: Apache-2.0
Classifier: Development Status :: 5 - Production/Stable
Classifier: Intended Audience :: Developers
Classifier: License :: Freely Distributable
Classifier: License :: OSI Approved :: Apache Software License
Classifier: Operating System :: OS Independent
Classifier: Programming Language :: Python
Classifier: Programming Language :: Python :: 3
Classifier: Programming Language :: Python :: 3.8
Classifier: Programming Language :: Python :: 3.9
Classifier: Programming Language :: Python :: 3.10
Classifier: Programming Language :: Python :: 3.11
Classifier: Programming Language :: Python :: 3.12
Classifier: Programming Language :: Python :: Implementation
Classifier: Programming Language :: Python :: Implementation :: CPython
Project-URL: Homepage, https://chaostoolkit.org/
Project-URL: Repository, https://github.com/chaostoolkit/chaostoolkit-lib
Project-URL: Documentation, https://chaostoolkit.org
Project-URL: Changelog, https://github.com/chaostoolkit/chaostoolkit-lib/blob/main/CHANGELOG.md
Requires-Python: >=3.8
Requires-Dist: requests>=2.31.0
Requires-Dist: pyyaml>=6.0.1
Requires-Dist: importlib-metadata>=6.7.0
Requires-Dist: charset-normalizer>=3.3.2
Requires-Dist: python-json-logger>=2.0.7
Requires-Dist: colorama>=0.4.4; sys_platform == "win32"
Requires-Dist: jsonpath2>=0.4.5; extra == "jsonpath"
Requires-Dist: hvac>=1.2.1; extra == "vault"
Provides-Extra: jsonpath
Provides-Extra: vault
